dl4dp/__init__.py
dl4dp/__main__.py
dl4dp/modules.py
dl4dp/parser.py
dl4dp/tagger.py
dl4dp/trainer.py
dl4dp/utils.py
dl4dp-0.9.1.dist-info/LICENSE
dl4dp-0.9.1.dist-info/METADATA
dl4dp-0.9.1.dist-info/WHEEL
dl4dp-0.9.1.dist-info/top_level.txt
dl4dp-0.9.1.dist-info/RECORD
