Metadata-Version: 2.1
Name: dl4dp
Version: 0.9.1
Summary: A Python library for morphological tagging, lemmatization and dependency parsing
Home-page: https://github.com/peterbednar/dl4dp
Author: Peter Bednár
Author-email: peter.bednar@tuke.sk
License: MIT
Platform: UNKNOWN
Classifier: Development Status :: 4 - Beta
Classifier: Intended Audience :: Developers
Classifier: Intended Audience :: Education
Classifier: Intended Audience :: Science/Research
Classifier: License :: OSI Approved :: MIT License
Classifier: Programming Language :: Python :: 3 :: Only
Classifier: Programming Language :: Python :: Implementation :: CPython
Classifier: Topic :: Text Processing :: Linguistic
Requires-Python: >=3.6
Requires-Dist: numpy
Requires-Dist: torch
Requires-Dist: pyyaml
Requires-Dist: requests
Requires-Dist: conllutils
